{
  "slug": "20260423-1776917453977",
  "title": "Google広告がさらに安全に、高速化へ。Ads Advisorの新機能3つが判明",
  "content": "<h1>Google、Ads Advisorに3つの新機能を統合——安全性と運用効率化を強化</h1>\n\n<p>Googleは、広告プラットフォーム「Google Ads」の管理ツール「Ads Advisor」に、エージェント型（自動実行）のセーフティ機能とポリシー遵守機能3つを統合することを明らかにした。これらの新機能により、広告主はアカウント保護と運用の効率化を同時に実現できるようになる。</p>\n\n<h2>AIが政策違反を自動検出——広告掲載停止のリスク軽減</h2>\n\n<p>新機能の中核をなすのが、AIエージェントによる自動監視システムだ。Ads Advisorは機械学習モデルを用いて、Google Adsポリシー違反のリスクを事前に検出し、広告主に警告を発する。従来は違反が発見された後の対応が主流だったが、今回の更新により予防的なアプローチが可能になった。Googleは、このシステムにより政策違反に基づく不承認や掲載停止の件数が大幅に減少すると見込んでいる。</p>\n\n<p>具体的には、広告テキストや画像、ランディングページの内容をリアルタイムで分析し、不適切な表現や虚偽の主張を自動判定する。これにより、広告主は手動でのポリシーチェックに費やす時間を削減でき、クリエイティブ制作やキャンペーン戦略に注力できるようになる。</p>\n\n<h2>自動最適化が広告効果を向上——運用の民主化を加速</h2>\n\n<p>もう一つの主要機能は、エージェント型の自動最適化機能だ。Ads Advisorはキャンペーン全体のパフォーマンスデータを分析し、入札戦略の調整やクリエイティブの改善案を自動提示する。これにより、データ分析スキルが限定的な中小企業でも、大企業並みの精度でキャンペーン管理が可能になる。</p>\n\n<p>さらに、新機能は複数キャンペーン間のクロス分析にも対応。全体的な予算配分の最適化や、低パフォーマンスキャンペーンの改善提案も自動生成される。Google側のデータでは、同類の自動最適化機能導入時に平均して広告効果が15～30%向上したとされており、今回の統合によっても同等以上の成果が期待できる。</p>\n\n<h2>業界への波及効果——競争激化の予兆</h2>\n\n<p>このような自動化・AI化の進展は、デジタル広告業界全体に大きな影響をもたらそうだ。広告運用の専門知識の重要性が低下する一方で、戦略立案やクリエイティブ企画といった創造的業務へのニーズが高まる。既に競合のMeta（Facebook）やAmazon Adsも、同様のエージェント機能の強化を進めており、各プラットフォーム間での機能競争が加速する見込みだ。</p>\n\n<p>Googleは同時に、広告主にとって「信頼できるAI」の構築を優先課題としており、過度な自動化による誤判定を防ぐため、人間による最終確認ステップを推奨している。今後、これらの新機能の実装状況と、ユーザーの満足度調査結果の公表に注目が集まりそうだ。</p>\n\n<p><a href=\"https://blog.google/products/ads-commerce/ads-advisor-google-ads/\" target=\"_blank\">参照元：Google AI Blog - 3 new ways Ads Advisor is making Google Ads safer and faster</a></p>",
  "imageUrl": "https://storage.googleapis.com/gweb-uniblog-publish-prod/images/Road_to_GML_Master-Header.max-600x600.format-webp.webp",
  "source": "Google AI",
  "sourceUrl": "https://blog.google/products/ads-commerce/ads-advisor-google-ads/",
  "publishedAt": "2026-04-23T04:10:53.978Z",
  "tags": [
    "AI",
    "テクノロジー",
    "Google AI"
  ]
}